dados_gov/__init__.py
dados_gov/api_client.py
dados_gov/http_response.py
dados_gov/settings.py
dados_gov/commons/__init__.py
dados_gov/commons/enhanced_json_encode.py
dados_gov/exceptions/__init__.py
dados_gov/exceptions/create_resource_exception.py
dados_gov/exceptions/edit_resource_exception.py
dados_gov/exceptions/http_request_exception.py
dados_gov/exceptions/list_resources_exception.py
dados_gov/exceptions/load_resource_exception.py
dados_gov/exceptions/update_resource_exception.py
dados_gov/models/__init__.py
dados_gov/models/base_model.py
dados_gov/models/dataset_model.py
dados_gov/models/resource_model.py
dados_gov/resources/__init__.py
dados_gov/resources/dataset_api.py
dados_gov/resources/requests_api.py
dados_gov/resources/resource_api.py
tests/__init__.py
tests/fixtures/__init__.py
tests/fixtures/api_resources_testcase_fixture.py
tests/fixtures/handle_file_fixture.py
tests/unittests/__init__.py
tests/unittests/test_dataset_api.py
tests/unittests/test_requests_api.py
tests/unittests/test_resource_api.py
tests/unittests/models/__init__.py
tests/unittests/models/test_dataset_model.py
tests/unittests/models/test_resource_model.py
dados_gov_sdk-1.1.0.dist-info/LICENSE
dados_gov_sdk-1.1.0.dist-info/METADATA
dados_gov_sdk-1.1.0.dist-info/WHEEL
dados_gov_sdk-1.1.0.dist-info/top_level.txt
dados_gov_sdk-1.1.0.dist-info/RECORD
