Metadata-Version: 2.1
Name: dados-gov-sdk
Version: 1.1.0
Summary: REST API of the Brazilian Federal Government Open Data Portal
Home-page: https://github.com/adrianolaselva/dados-gov-python-sdk.git
Author: Adriano M. La Selva
Author-email: adrianolaselva@gmail.com
License: MIT
Keywords: python,dados,data,api,apis,recursos,resources,swagger,client,sdk,pygov,swagger,portal,gov,governo,government,federal,brasil,brazil,api,swagger,abertos,open,open-data,transparencia,transparency,utilitario,utility,colaborativo,collaborative,modulo,module,pacote,package
Classifier: Development Status :: 5 - Production/Stable
Classifier: Intended Audience :: Developers
Classifier: Topic :: Software Development :: Build Tools
Classifier: Programming Language :: Python :: 3.8
Classifier: Programming Language :: Python :: 3.9
Classifier: Programming Language :: Python :: 3.11
Classifier: Programming Language :: Python :: 3 :: Only
Classifier: License :: OSI Approved :: MIT License
License-File: LICENSE
Requires-Dist: certifi >=14.05.14
Requires-Dist: six >=1.10
Requires-Dist: setuptools >=21.0.0
Requires-Dist: urllib3 >=1.15.1
Requires-Dist: requests >=2.31.0
